[
  {
    "address": "9077 Pine Dr",
    "city": "Denver",
    "state": "CO",
    "zip": "80260",
    "county": "Denver County",
    "latitude": 39.716257,
    "longitude": -105.060357,
    "bedrooms": 4,
    "bathrooms": 1.0,
    "square_feet": 2066,
    "lot_size": 0.33,
    "year_built": 2013,
    "garage_spaces": 1,
    "basement": false,
    "pool": false,
    "fireplace": false,
    "property_type": "Single Family",
    "market_value": 339548,
    "tax_assessment": 293985,
    "insurance_value": 413371,
    "rental_estimate": 3814,
    "flooring_cost": 5129,
    "electrical_work": 5488,
    "interior_paint": 2467,
    "data_source": "Sample Generator",
    "created_date": "2025-08-20T16:46:16.974144",
    "property_id": "PROP_407180"
  },
  {
    "address": "8695 Oak Ave",
    "city": "Houston",
    "state": "TX",
    "zip": "77098",
    "county": "Houston County",
    "latitude": 29.678396,
    "longitude": -95.455958,
    "bedrooms": 3,
    "bathrooms": 1.0,
    "square_feet": 1721,
    "lot_size": 1.93,
    "year_built": 2006,
    "garage_spaces": 0,
    "basement": true,
    "pool": true,
    "fireplace": false,
    "property_type": "Duplex",
    "market_value": 403621,
    "tax_assessment": 326888,
    "insurance_value": 466986,
    "rental_estimate": 4510,
    "hoa_name": "Sunset Hills HOA",
    "hoa_monthly_fee": 472,
    "hoa_special_assessment": 0,
    "hoa_amenities": "Tennis Court, Walking Trails",
    "hoa_management": "ABC Property Management",
    "bathroom_rehab": 8559,
    "flooring_cost": 2369,
    "electrical_work": 3058,
    "interior_paint": 4713,
    "exterior_paint": 4737,
    "data_source": "Sample Generator",
    "created_date": "2025-08-20T16:46:16.974193",
    "property_id": "PROP_406311"
  },
  {
    "address": "8385 Park Ave",
    "city": "Nashville",
    "state": "TN",
    "zip": "37200",
    "county": "Nashville County",
    "latitude": 36.151315,
    "longitude": -86.703865,
    "bedrooms": 4,
    "bathrooms": 2.0,
    "square_feet": 2323,
    "lot_size": 1.59,
    "year_built": 2023,
    "garage_spaces": 1,
    "basement": true,
    "pool": true,
    "fireplace": false,
    "property_type": "Townhouse",
    "market_value": 353730,
    "tax_assessment": 315907,
    "insurance_value": 397316,
    "rental_estimate": 2820,
    "bathroom_rehab": 9671,
    "exterior_paint": 3245,
    "data_source": "Sample Generator",
    "created_date": "2025-08-20T16:46:16.974225",
    "property_id": "PROP_719275"
  },
  {
    "address": "1004 Park Ave",
    "city": "Denver",
    "state": "CO",
    "zip": "80224",
    "county": "Denver County",
    "latitude": 39.69683,
    "longitude": -104.962813,
    "bedrooms": 6,
    "bathrooms": 1.0,
    "square_feet": 3191,
    "lot_size": 1.78,
    "year_built": 2012,
    "garage_spaces": 2,
    "basement": true,
    "pool": false,
    "fireplace": false,
    "property_type": "Single Family",
    "market_value": 866944,
    "tax_assessment": 720982,
    "insurance_value": 1080794,
    "rental_estimate": 9578,
    "kitchen_rehab": 14927,
    "exterior_paint": 4837,
    "data_source": "Sample Generator",
    "created_date": "2025-08-20T16:46:16.974252",
    "property_id": "PROP_777582"
  },
  {
    "address": "3315 Second St",
    "city": "Charlotte",
    "state": "NC",
    "zip": "28266",
    "county": "Charlotte County",
    "latitude": 35.219142,
    "longitude": -80.759744,
    "bedrooms": 4,
    "bathrooms": 3.5,
    "square_feet": 1766,
    "lot_size": 0.3,
    "year_built": 1993,
    "garage_spaces": 2,
    "basement": false,
    "pool": false,
    "fireplace": true,
    "property_type": "Duplex",
    "market_value": 293540,
    "tax_assessment": 213230,
    "insurance_value": 360459,
    "rental_estimate": 3501,
    "hoa_name": "Oak Ridge Community",
    "hoa_monthly_fee": 345,
    "hoa_special_assessment": 0,
    "hoa_amenities": "Clubhouse, Pool, Gym",
    "hoa_management": "ABC Property Management",
    "electrical_work": 7839,
    "plumbing_work": 3722,
    "flooring_cost": 10509,
    "roof_repair": 12773,
    "data_source": "Sample Generator",
    "created_date": "2025-08-20T16:46:16.974284",
    "property_id": "PROP_669188"
  },
  {
    "address": "5268 Second St",
    "city": "Phoenix",
    "state": "AZ",
    "zip": "85095",
    "county": "Phoenix County",
    "latitude": 33.389023,
    "longitude": -112.11553,
    "bedrooms": 5,
    "bathrooms": 3.5,
    "square_feet": 2545,
    "lot_size": 1.21,
    "year_built": 2002,
    "garage_spaces": 0,
    "basement": true,
    "pool": true,
    "fireplace": false,
    "property_type": "Multi-Family",
    "market_value": 355360,
    "tax_assessment": 281030,
    "insurance_value": 418953,
    "rental_estimate": 3408,
    "hoa_name": "Oak Ridge Community",
    "hoa_monthly_fee": 167,
    "hoa_special_assessment": 0,
    "hoa_amenities": "Playground, Clubhouse",
    "hoa_management": "XYZ HOA Services",
    "roof_repair": 12039,
    "interior_paint": 4128,
    "hvac_cost": 8425,
    "exterior_paint": 4235,
    "data_source": "Sample Generator",
    "created_date": "2025-08-20T16:46:16.974315",
    "property_id": "PROP_260326"
  },
  {
    "address": "7524 Park Ave",
    "city": "Austin",
    "state": "TX",
    "zip": "78758",
    "county": "Austin County",
    "latitude": 30.27251,
    "longitude": -97.718966,
    "bedrooms": 4,
    "bathrooms": 1.5,
    "square_feet": 1977,
    "lot_size": 0.57,
    "year_built": 1991,
    "garage_spaces": 0,
    "basement": true,
    "pool": true,
    "fireplace": false,
    "property_type": "Townhouse",
    "market_value": 331248,
    "tax_assessment": 287031,
    "insurance_value": 429937,
    "rental_estimate": 2731,
    "flooring_cost": 2664,
    "roof_repair": 14090,
    "hvac_cost": 9748,
    "interior_paint": 2211,
    "exterior_paint": 7844,
    "data_source": "Sample Generator",
    "created_date": "2025-08-20T16:46:16.974345",
    "property_id": "PROP_588585"
  },
  {
    "address": "9374 Second St",
    "city": "Nashville",
    "state": "TN",
    "zip": "37218",
    "county": "Nashville County",
    "latitude": 36.168735,
    "longitude": -86.750346,
    "bedrooms": 4,
    "bathrooms": 4.0,
    "square_feet": 1636,
    "lot_size": 0.72,
    "year_built": 2015,
    "garage_spaces": 1,
    "basement": true,
    "pool": false,
    "fireplace": false,
    "property_type": "Condo",
    "market_value": 310506,
    "tax_assessment": 226329,
    "insurance_value": 367977,
    "rental_estimate": 3175,
    "hoa_name": "Cedar Creek Community",
    "hoa_monthly_fee": 291,
    "hoa_special_assessment": 0,
    "hoa_amenities": "Tennis Court, Walking Trails",
    "hoa_management": "Community First Management",
    "flooring_cost": 9858,
    "interior_paint": 4308,
    "data_source": "Sample Generator",
    "created_date": "2025-08-20T16:46:16.974373",
    "property_id": "PROP_519885"
  },
  {
    "address": "1235 Highland Dr",
    "city": "Charlotte",
    "state": "NC",
    "zip": "28251",
    "county": "Charlotte County",
    "latitude": 35.189189,
    "longitude": -80.775798,
    "bedrooms": 4,
    "bathrooms": 2.0,
    "square_feet": 2351,
    "lot_size": 0.41,
    "year_built": 1997,
    "garage_spaces": 2,
    "basement": true,
    "pool": false,
    "fireplace": false,
    "property_type": "Townhouse",
    "market_value": 347685,
    "tax_assessment": 262897,
    "insurance_value": 394382,
    "rental_estimate": 2306,
    "roof_repair": 15717,
    "bathroom_rehab": 10038,
    "data_source": "Sample Generator",
    "created_date": "2025-08-20T16:46:16.974398",
    "property_id": "PROP_813547"
  },
  {
    "address": "7419 Valley Dr",
    "city": "Austin",
    "state": "TX",
    "zip": "78735",
    "county": "Austin County",
    "latitude": 30.1864,
    "longitude": -97.68153,
    "bedrooms": 4,
    "bathrooms": 2.5,
    "square_feet": 2123,
    "lot_size": 0.28,
    "year_built": 1998,
    "garage_spaces": 3,
    "basement": true,
    "pool": false,
    "fireplace": false,
    "property_type": "Townhouse",
    "market_value": 426954,
    "tax_assessment": 334561,
    "insurance_value": 473935,
    "rental_estimate": 4773,
    "electrical_work": 6485,
    "kitchen_rehab": 7337,
    "plumbing_work": 5710,
    "interior_paint": 4690,
    "data_source": "Sample Generator",
    "created_date": "2025-08-20T16:46:16.974432",
    "property_id": "PROP_343711"
  },
  {
    "address": "8937 Hill St",
    "city": "Dallas",
    "state": "TX",
    "zip": "75224",
    "county": "Dallas County",
    "latitude": 32.850082,
    "longitude": -96.833563,
    "bedrooms": 4,
    "bathrooms": 4.0,
    "square_feet": 1624,
    "lot_size": 0.65,
    "year_built": 1980,
    "garage_spaces": 0,
    "basement": true,
    "pool": false,
    "fireplace": false,
    "property_type": "Single Family",
    "market_value": 310577,
    "tax_assessment": 271127,
    "insurance_value": 371640,
    "rental_estimate": 2449,
    "flooring_cost": 2058,
    "bathroom_rehab": 5627,
    "kitchen_rehab": 10047,
    "interior_paint": 3099,
    "data_source": "Sample Generator",
    "created_date": "2025-08-20T16:46:16.974461",
    "property_id": "PROP_650501"
  },
  {
    "address": "1525 Pine Dr",
    "city": "Austin",
    "state": "TX",
    "zip": "78761",
    "county": "Austin County",
    "latitude": 30.187184,
    "longitude": -97.783265,
    "bedrooms": 2,
    "bathrooms": 1.5,
    "square_feet": 1363,
    "lot_size": 1.63,
    "year_built": 2010,
    "garage_spaces": 3,
    "basement": true,
    "pool": false,
    "fireplace": true,
    "property_type": "Duplex",
    "market_value": 358732,
    "tax_assessment": 290964,
    "insurance_value": 460980,
    "rental_estimate": 1848,
    "hoa_name": "Pine Valley Association",
    "hoa_monthly_fee": 51,
    "hoa_special_assessment": 0,
    "hoa_amenities": "Pool, Spa",
    "hoa_management": "XYZ HOA Services",
    "electrical_work": 7744,
    "roof_repair": 10988,
    "hvac_cost": 11149,
    "plumbing_work": 2956,
    "interior_paint": 1196,
    "data_source": "Sample Generator",
    "created_date": "2025-08-20T16:46:16.974496",
    "property_id": "PROP_171703"
  },
  {
    "address": "1645 Cedar Ln",
    "city": "Dallas",
    "state": "TX",
    "zip": "75206",
    "county": "Dallas County",
    "latitude": 32.806488,
    "longitude": -96.741545,
    "bedrooms": 4,
    "bathrooms": 2.5,
    "square_feet": 1897,
    "lot_size": 1.65,
    "year_built": 2010,
    "garage_spaces": 3,
    "basement": true,
    "pool": false,
    "fireplace": false,
    "property_type": "Townhouse",
    "market_value": 406946,
    "tax_assessment": 287351,
    "insurance_value": 455224,
    "rental_estimate": 2271,
    "kitchen_rehab": 5110,
    "electrical_work": 2491,
    "interior_paint": 3887,
    "exterior_paint": 7549,
    "data_source": "Sample Generator",
    "created_date": "2025-08-20T16:46:16.974523",
    "property_id": "PROP_690461"
  },
  {
    "address": "5448 Oak Ave",
    "city": "Denver",
    "state": "CO",
    "zip": "80249",
    "county": "Denver County",
    "latitude": 39.740133,
    "longitude": -104.983405,
    "bedrooms": 2,
    "bathrooms": 3.5,
    "square_feet": 1467,
    "lot_size": 1.95,
    "year_built": 1991,
    "garage_spaces": 1,
    "basement": true,
    "pool": true,
    "fireplace": false,
    "property_type": "Multi-Family",
    "market_value": 169251,
    "tax_assessment": 121802,
    "insurance_value": 195710,
    "rental_estimate": 919,
    "roof_repair": 16800,
    "hvac_cost": 5092,
    "data_source": "Sample Generator",
    "created_date": "2025-08-20T16:46:16.974548",
    "property_id": "PROP_767625"
  },
  {
    "address": "9306 Park Ave",
    "city": "Atlanta",
    "state": "GA",
    "zip": "30333",
    "county": "Atlanta County",
    "latitude": 33.666902,
    "longitude": -84.480159,
    "bedrooms": 3,
    "bathrooms": 2.5,
    "square_feet": 1469,
    "lot_size": 1.84,
    "year_built": 2013,
    "garage_spaces": 3,
    "basement": true,
    "pool": true,
    "fireplace": false,
    "property_type": "Duplex",
    "market_value": 327286,
    "tax_assessment": 283015,
    "insurance_value": 387792,
    "rental_estimate": 2914,
    "hoa_name": "Sunset Hills HOA",
    "hoa_monthly_fee": 206,
    "hoa_special_assessment": 0,
    "hoa_amenities": "Pool, Spa",
    "hoa_management": "ABC Property Management",
    "bathroom_rehab": 11435,
    "interior_paint": 4855,
    "roof_repair": 17510,
    "flooring_cost": 9035,
    "plumbing_work": 2646,
    "data_source": "Sample Generator",
    "created_date": "2025-08-20T16:46:16.974580",
    "property_id": "PROP_136049"
  },
  {
    "address": "2350 First St",
    "city": "Atlanta",
    "state": "GA",
    "zip": "30313",
    "county": "Atlanta County",
    "latitude": 33.686853,
    "longitude": -84.409967,
    "bedrooms": 5,
    "bathrooms": 2.5,
    "square_feet": 2657,
    "lot_size": 1.86,
    "year_built": 1997,
    "garage_spaces": 0,
    "basement": true,
    "pool": false,
    "fireplace": false,
    "property_type": "Condo",
    "market_value": 384585,
    "tax_assessment": 345898,
    "insurance_value": 496213,
    "rental_estimate": 3081,
    "hoa_name": "Pine Valley Association",
    "hoa_monthly_fee": 344,
    "hoa_special_assessment": 0,
    "hoa_amenities": "Pool, Gym, Tennis Court",
    "hoa_management": "Premier HOA Solutions",
    "electrical_work": 7131,
    "hvac_cost": 4163,
    "bathroom_rehab": 6588,
    "plumbing_work": 3289,
    "data_source": "Sample Generator",
    "created_date": "2025-08-20T16:46:16.974609",
    "property_id": "PROP_335034"
  },
  {
    "address": "9742 Main St",
    "city": "Charlotte",
    "state": "NC",
    "zip": "28267",
    "county": "Charlotte County",
    "latitude": 35.242962,
    "longitude": -80.776737,
    "bedrooms": 6,
    "bathrooms": 4.0,
    "square_feet": 3021,
    "lot_size": 0.85,
    "year_built": 2000,
    "garage_spaces": 1,
    "basement": true,
    "pool": true,
    "fireplace": false,
    "property_type": "Duplex",
    "market_value": 566537,
    "tax_assessment": 472911,
    "insurance_value": 649365,
    "rental_estimate": 2845,
    "hoa_name": "Pine Valley Association",
    "hoa_monthly_fee": 439,
    "hoa_special_assessment": 0,
    "hoa_amenities": "Pool, Gym, Tennis Court",
    "hoa_management": "Premier HOA Solutions",
    "hvac_cost": 4185,
    "plumbing_work": 1865,
    "interior_paint": 1589,
    "flooring_cost": 8796,
    "roof_repair": 14749,
    "data_source": "Sample Generator",
    "created_date": "2025-08-20T16:46:16.974640",
    "property_id": "PROP_929960"
  },
  {
    "address": "4358 Sunset Blvd",
    "city": "Austin",
    "state": "TX",
    "zip": "78707",
    "county": "Austin County",
    "latitude": 30.338276,
    "longitude": -97.729693,
    "bedrooms": 2,
    "bathrooms": 2.0,
    "square_feet": 864,
    "lot_size": 1.69,
    "year_built": 2005,
    "garage_spaces": 1,
    "basement": false,
    "pool": false,
    "fireplace": false,
    "property_type": "Single Family",
    "market_value": 182535,
    "tax_assessment": 142333,
    "insurance_value": 213195,
    "rental_estimate": 1249,
    "hoa_name": "Maple Grove HOA",
    "hoa_monthly_fee": 115,
    "hoa_special_assessment": 0,
    "hoa_amenities": "Pool, Spa",
    "hoa_management": "ABC Property Management",
    "plumbing_work": 1612,
    "hvac_cost": 5293,
    "data_source": "Sample Generator",
    "created_date": "2025-08-20T16:46:16.974667",
    "property_id": "PROP_423493"
  },
  {
    "address": "4147 Second St",
    "city": "Charlotte",
    "state": "NC",
    "zip": "28213",
    "county": "Charlotte County",
    "latitude": 35.130446,
    "longitude": -80.807799,
    "bedrooms": 4,
    "bathrooms": 3.5,
    "square_feet": 1616,
    "lot_size": 0.23,
    "year_built": 2020,
    "garage_spaces": 0,
    "basement": false,
    "pool": false,
    "fireplace": false,
    "property_type": "Multi-Family",
    "market_value": 326455,
    "tax_assessment": 235699,
    "insurance_value": 421141,
    "rental_estimate": 2117,
    "plumbing_work": 2502,
    "roof_repair": 15589,
    "exterior_paint": 3452,
    "data_source": "Sample Generator",
    "created_date": "2025-08-20T16:46:16.974693",
    "property_id": "PROP_589906"
  },
  {
    "address": "1241 Valley Dr",
    "city": "Charlotte",
    "state": "NC",
    "zip": "28215",
    "county": "Charlotte County",
    "latitude": 35.213966,
    "longitude": -80.900336,
    "bedrooms": 4,
    "bathrooms": 1.0,
    "square_feet": 2178,
    "lot_size": 0.74,
    "year_built": 1992,
    "garage_spaces": 0,
    "basement": true,
    "pool": false,
    "fireplace": false,
    "property_type": "Multi-Family",
    "market_value": 556223,
    "tax_assessment": 399742,
    "insurance_value": 657593,
    "rental_estimate": 5147,
    "kitchen_rehab": 21597,
    "electrical_work": 4669,
    "hvac_cost": 6355,
    "interior_paint": 2750,
    "exterior_paint": 5288,
    "data_source": "Sample Generator",
    "created_date": "2025-08-20T16:46:16.974727",
    "property_id": "PROP_467102"
  },
  {
    "address": "189 Elm St",
    "city": "Charlotte",
    "state": "NC",
    "zip": "28217",
    "county": "Charlotte County",
    "latitude": 35.234266,
    "longitude": -80.762014,
    "bedrooms": 2,
    "bathrooms": 1.5,
    "square_feet": 1385,
    "lot_size": 1.3,
    "year_built": 1982,
    "garage_spaces": 2,
    "basement": false,
    "pool": false,
    "fireplace": false,
    "property_type": "Multi-Family",
    "market_value": 316733,
    "tax_assessment": 283032,
    "insurance_value": 359492,
    "rental_estimate": 2072,
    "roof_repair": 17780,
    "hvac_cost": 11827,
    "bathroom_rehab": 7752,
    "flooring_cost": 2286,
    "data_source": "Sample Generator",
    "created_date": "2025-08-20T16:46:16.974756",
    "property_id": "PROP_667856"
  },
  {
    "address": "2308 Maple Way",
    "city": "Nashville",
    "state": "TN",
    "zip": "37252",
    "county": "Nashville County",
    "latitude": 36.250278,
    "longitude": -86.716265,
    "bedrooms": 3,
    "bathrooms": 1.5,
    "square_feet": 1863,
    "lot_size": 1.77,
    "year_built": 1995,
    "garage_spaces": 3,
    "basement": true,
    "pool": false,
    "fireplace": false,
    "property_type": "Duplex",
    "market_value": 168179,
    "tax_assessment": 131719,
    "insurance_value": 211318,
    "rental_estimate": 1739,
    "hvac_cost": 6142,
    "flooring_cost": 5117,
    "exterior_paint": 3138,
    "kitchen_rehab": 8494,
    "interior_paint": 3705,
    "data_source": "Sample Generator",
    "created_date": "2025-08-20T16:46:16.974785",
    "property_id": "PROP_950495"
  },
  {
    "address": "596 Pine Dr",
    "city": "Denver",
    "state": "CO",
    "zip": "80282",
    "county": "Denver County",
    "latitude": 39.743401,
    "longitude": -104.900921,
    "bedrooms": 4,
    "bathrooms": 4.0,
    "square_feet": 1601,
    "lot_size": 1.54,
    "year_built": 2014,
    "garage_spaces": 1,
    "basement": true,
    "pool": false,
    "fireplace": false,
    "property_type": "Multi-Family",
    "market_value": 498079,
    "tax_assessment": 355850,
    "insurance_value": 590019,
    "rental_estimate": 5410,
    "hoa_name": "Sunset Hills HOA",
    "hoa_monthly_fee": 125,
    "hoa_special_assessment": 0,
    "hoa_amenities": "Clubhouse, Pool, Gym",
    "hoa_management": "ABC Property Management",
    "electrical_work": 7949,
    "flooring_cost": 8085,
    "data_source": "Sample Generator",
    "created_date": "2025-08-20T16:46:16.974811",
    "property_id": "PROP_815267"
  },
  {
    "address": "1101 Valley Dr",
    "city": "Nashville",
    "state": "TN",
    "zip": "37221",
    "county": "Nashville County",
    "latitude": 36.215896,
    "longitude": -86.726875,
    "bedrooms": 4,
    "bathrooms": 1.0,
    "square_feet": 1918,
    "lot_size": 1.62,
    "year_built": 1998,
    "garage_spaces": 1,
    "basement": true,
    "pool": false,
    "fireplace": true,
    "property_type": "Duplex",
    "market_value": 271253,
    "tax_assessment": 206400,
    "insurance_value": 344844,
    "rental_estimate": 1494,
    "hoa_name": "Sunset Hills HOA",
    "hoa_monthly_fee": 476,
    "hoa_special_assessment": 0,
    "hoa_amenities": "Pool, Gym, Tennis Court",
    "hoa_management": "XYZ HOA Services",
    "hvac_cost": 10103,
    "plumbing_work": 4503,
    "roof_repair": 8702,
    "data_source": "Sample Generator",
    "created_date": "2025-08-20T16:46:16.974840",
    "property_id": "PROP_105571"
  },
  {
    "address": "508 Maple Way",
    "city": "Austin",
    "state": "TX",
    "zip": "78721",
    "county": "Austin County",
    "latitude": 30.361822,
    "longitude": -97.778764,
    "bedrooms": 5,
    "bathrooms": 2.5,
    "square_feet": 2528,
    "lot_size": 1.85,
    "year_built": 1996,
    "garage_spaces": 3,
    "basement": true,
    "pool": false,
    "fireplace": false,
    "property_type": "Multi-Family",
    "market_value": 597473,
    "tax_assessment": 528142,
    "insurance_value": 770994,
    "rental_estimate": 4830,
    "electrical_work": 2249,
    "bathroom_rehab": 10952,
    "interior_paint": 4329,
    "data_source": "Sample Generator",
    "created_date": "2025-08-20T16:46:16.974864",
    "property_id": "PROP_782623"
  },
  {
    "address": "3200 Maple Way",
    "city": "Phoenix",
    "state": "AZ",
    "zip": "85072",
    "county": "Phoenix County",
    "latitude": 33.363396,
    "longitude": -112.06307,
    "bedrooms": 4,
    "bathrooms": 2.0,
    "square_feet": 1716,
    "lot_size": 0.75,
    "year_built": 1996,
    "garage_spaces": 3,
    "basement": false,
    "pool": false,
    "fireplace": false,
    "property_type": "Duplex",
    "market_value": 334959,
    "tax_assessment": 258028,
    "insurance_value": 394787,
    "rental_estimate": 3286,
    "electrical_work": 2024,
    "plumbing_work": 2274,
    "flooring_cost": 5655,
    "roof_repair": 13851,
    "data_source": "Sample Generator",
    "created_date": "2025-08-20T16:46:16.974891",
    "property_id": "PROP_505532"
  },
  {
    "address": "3592 Third St",
    "city": "Austin",
    "state": "TX",
    "zip": "78788",
    "county": "Austin County",
    "latitude": 30.218038,
    "longitude": -97.649159,
    "bedrooms": 3,
    "bathrooms": 1.0,
    "square_feet": 1559,
    "lot_size": 1.11,
    "year_built": 1981,
    "garage_spaces": 1,
    "basement": false,
    "pool": false,
    "fireplace": false,
    "property_type": "Condo",
    "market_value": 353968,
    "tax_assessment": 261750,
    "insurance_value": 414465,
    "rental_estimate": 2519,
    "exterior_paint": 4880,
    "bathroom_rehab": 4648,
    "data_source": "Sample Generator",
    "created_date": "2025-08-20T16:46:16.974915",
    "property_id": "PROP_508994"
  },
  {
    "address": "1349 Cedar Ln",
    "city": "Austin",
    "state": "TX",
    "zip": "78797",
    "county": "Austin County",
    "latitude": 30.317291,
    "longitude": -97.670952,
    "bedrooms": 3,
    "bathrooms": 2.5,
    "square_feet": 1369,
    "lot_size": 1.64,
    "year_built": 2005,
    "garage_spaces": 0,
    "basement": false,
    "pool": false,
    "fireplace": false,
    "property_type": "Townhouse",
    "market_value": 303369,
    "tax_assessment": 267291,
    "insurance_value": 367445,
    "rental_estimate": 1856,
    "flooring_cost": 5919,
    "bathroom_rehab": 14461,
    "data_source": "Sample Generator",
    "created_date": "2025-08-20T16:46:16.974939",
    "property_id": "PROP_358549"
  },
  {
    "address": "239 Park Ave",
    "city": "Houston",
    "state": "TX",
    "zip": "77010",
    "county": "Houston County",
    "latitude": 29.725091,
    "longitude": -95.357512,
    "bedrooms": 3,
    "bathrooms": 3.0,
    "square_feet": 1980,
    "lot_size": 1.22,
    "year_built": 2001,
    "garage_spaces": 0,
    "basement": true,
    "pool": false,
    "fireplace": false,
    "property_type": "Duplex",
    "market_value": 181638,
    "tax_assessment": 130417,
    "insurance_value": 213397,
    "rental_estimate": 2010,
    "hoa_name": "Cedar Creek Community",
    "hoa_monthly_fee": 257,
    "hoa_special_assessment": 0,
    "hoa_amenities": "Pool, Gym, Tennis Court",
    "hoa_management": "XYZ HOA Services",
    "electrical_work": 7254,
    "flooring_cost": 8190,
    "data_source": "Sample Generator",
    "created_date": "2025-08-20T16:46:16.974965",
    "property_id": "PROP_643517"
  },
  {
    "address": "2724 Park Ave",
    "city": "Atlanta",
    "state": "GA",
    "zip": "30364",
    "county": "Atlanta County",
    "latitude": 33.702715,
    "longitude": -84.439569,
    "bedrooms": 4,
    "bathrooms": 2.5,
    "square_feet": 2398,
    "lot_size": 1.7,
    "year_built": 1975,
    "garage_spaces": 1,
    "basement": false,
    "pool": false,
    "fireplace": false,
    "property_type": "Single Family",
    "market_value": 633771,
    "tax_assessment": 470167,
    "insurance_value": 744852,
    "rental_estimate": 6248,
    "hoa_name": "Riverside HOA",
    "hoa_monthly_fee": 377,
    "hoa_special_assessment": 0,
    "hoa_amenities": "Tennis Court, Walking Trails",
    "hoa_management": "XYZ HOA Services",
    "interior_paint": 1480,
    "roof_repair": 19225,
    "bathroom_rehab": 3545,
    "data_source": "Sample Generator",
    "created_date": "2025-08-20T16:46:16.974997",
    "property_id": "PROP_905067"
  },
  {
    "address": "7124 Hill St",
    "city": "Phoenix",
    "state": "AZ",
    "zip": "85072",
    "county": "Phoenix County",
    "latitude": 33.507746,
    "longitude": -111.988251,
    "bedrooms": 5,
    "bathrooms": 3.0,
    "square_feet": 2135,
    "lot_size": 1.48,
    "year_built": 1994,
    "garage_spaces": 1,
    "basement": true,
    "pool": false,
    "fireplace": false,
    "property_type": "Condo",
    "market_value": 277876,
    "tax_assessment": 238797,
    "insurance_value": 312137,
    "rental_estimate": 3325,
    "interior_paint": 3385,
    "electrical_work": 2288,
    "bathroom_rehab": 11929,
    "hvac_cost": 10844,
    "data_source": "Sample Generator",
    "created_date": "2025-08-20T16:46:16.975026",
    "property_id": "PROP_702118"
  },
  {
    "address": "4407 Valley Dr",
    "city": "Denver",
    "state": "CO",
    "zip": "80228",
    "county": "Denver County",
    "latitude": 39.73663,
    "longitude": -105.086582,
    "bedrooms": 5,
    "bathrooms": 3.0,
    "square_feet": 2748,
    "lot_size": 0.43,
    "year_built": 1996,
    "garage_spaces": 0,
    "basement": false,
    "pool": false,
    "fireplace": false,
    "property_type": "Multi-Family",
    "market_value": 692084,
    "tax_assessment": 602031,
    "insurance_value": 800161,
    "rental_estimate": 7284,
    "interior_paint": 1193,
    "bathroom_rehab": 14195,
    "data_source": "Sample Generator",
    "created_date": "2025-08-20T16:46:16.975052",
    "property_id": "PROP_542075"
  },
  {
    "address": "1946 Second St",
    "city": "Dallas",
    "state": "TX",
    "zip": "75274",
    "county": "Dallas County",
    "latitude": 32.723614,
    "longitude": -96.735021,
    "bedrooms": 3,
    "bathrooms": 2.5,
    "square_feet": 1255,
    "lot_size": 0.95,
    "year_built": 2002,
    "garage_spaces": 1,
    "basement": true,
    "pool": false,
    "fireplace": true,
    "property_type": "Multi-Family",
    "market_value": 328643,
    "tax_assessment": 290489,
    "insurance_value": 401453,
    "rental_estimate": 2989,
    "kitchen_rehab": 8347,
    "flooring_cost": 11604,
    "exterior_paint": 3388,
    "plumbing_work": 3395,
    "data_source": "Sample Generator",
    "created_date": "2025-08-20T16:46:16.975080",
    "property_id": "PROP_927692"
  },
  {
    "address": "2062 Park Ave",
    "city": "Phoenix",
    "state": "AZ",
    "zip": "85011",
    "county": "Phoenix County",
    "latitude": 33.399654,
    "longitude": -112.126607,
    "bedrooms": 4,
    "bathrooms": 2.5,
    "square_feet": 1812,
    "lot_size": 1.03,
    "year_built": 1991,
    "garage_spaces": 0,
    "basement": true,
    "pool": true,
    "fireplace": false,
    "property_type": "Condo",
    "market_value": 234463,
    "tax_assessment": 172110,
    "insurance_value": 285842,
    "rental_estimate": 1561,
    "bathroom_rehab": 14084,
    "electrical_work": 7892,
    "hvac_cost": 7943,
    "roof_repair": 13842,
    "flooring_cost": 9716,
    "data_source": "Sample Generator",
    "created_date": "2025-08-20T16:46:16.975107",
    "property_id": "PROP_838002"
  },
  {
    "address": "8605 Second St",
    "city": "Phoenix",
    "state": "AZ",
    "zip": "85013",
    "county": "Phoenix County",
    "latitude": 33.543533,
    "longitude": -112.091427,
    "bedrooms": 5,
    "bathrooms": 2.0,
    "square_feet": 2500,
    "lot_size": 0.74,
    "year_built": 1999,
    "garage_spaces": 0,
    "basement": true,
    "pool": false,
    "fireplace": false,
    "property_type": "Condo",
    "market_value": 354090,
    "tax_assessment": 272122,
    "insurance_value": 422746,
    "rental_estimate": 3214,
    "hvac_cost": 6791,
    "interior_paint": 1747,
    "exterior_paint": 6871,
    "electrical_work": 6479,
    "data_source": "Sample Generator",
    "created_date": "2025-08-20T16:46:16.975134",
    "property_id": "PROP_717848"
  },
  {
    "address": "2714 Valley Dr",
    "city": "Charlotte",
    "state": "NC",
    "zip": "28227",
    "county": "Charlotte County",
    "latitude": 35.235757,
    "longitude": -80.89737,
    "bedrooms": 4,
    "bathrooms": 3.0,
    "square_feet": 2206,
    "lot_size": 0.82,
    "year_built": 1977,
    "garage_spaces": 0,
    "basement": true,
    "pool": false,
    "fireplace": false,
    "property_type": "Single Family",
    "market_value": 253045,
    "tax_assessment": 203271,
    "insurance_value": 322655,
    "rental_estimate": 2812,
    "interior_paint": 4414,
    "hvac_cost": 7052,
    "electrical_work": 2792,
    "bathroom_rehab": 11656,
    "data_source": "Sample Generator",
    "created_date": "2025-08-20T16:46:16.975160",
    "property_id": "PROP_745766"
  },
  {
    "address": "3912 Park Ave",
    "city": "Nashville",
    "state": "TN",
    "zip": "37228",
    "county": "Nashville County",
    "latitude": 36.238947,
    "longitude": -86.76393,
    "bedrooms": 4,
    "bathrooms": 3.0,
    "square_feet": 2220,
    "lot_size": 1.34,
    "year_built": 1999,
    "garage_spaces": 2,
    "basement": true,
    "pool": true,
    "fireplace": true,
    "property_type": "Duplex",
    "market_value": 440373,
    "tax_assessment": 312317,
    "insurance_value": 524542,
    "rental_estimate": 4246,
    "hoa_name": "Sunset Hills HOA",
    "hoa_monthly_fee": 361,
    "hoa_special_assessment": 0,
    "hoa_amenities": "Tennis Court, Walking Trails",
    "hoa_management": "ABC Property Management",
    "electrical_work": 3758,
    "bathroom_rehab": 7808,
    "exterior_paint": 3914,
    "hvac_cost": 4218,
    "plumbing_work": 3906,
    "data_source": "Sample Generator",
    "created_date": "2025-08-20T16:46:16.975192",
    "property_id": "PROP_577756"
  },
  {
    "address": "4491 River Rd",
    "city": "Atlanta",
    "state": "GA",
    "zip": "30394",
    "county": "Atlanta County",
    "latitude": 33.798914,
    "longitude": -84.329136,
    "bedrooms": 3,
    "bathrooms": 1.5,
    "square_feet": 1384,
    "lot_size": 1.89,
    "year_built": 1997,
    "garage_spaces": 3,
    "basement": true,
    "pool": false,
    "fireplace": false,
    "property_type": "Duplex",
    "market_value": 245580,
    "tax_assessment": 213485,
    "insurance_value": 301859,
    "rental_estimate": 2190,
    "hoa_name": "Maple Grove HOA",
    "hoa_monthly_fee": 225,
    "hoa_special_assessment": 0,
    "hoa_amenities": "Pool, Spa",
    "hoa_management": "Premier HOA Solutions",
    "kitchen_rehab": 9908,
    "plumbing_work": 2640,
    "data_source": "Sample Generator",
    "created_date": "2025-08-20T16:46:16.975218",
    "property_id": "PROP_896837"
  },
  {
    "address": "6536 Pine Dr",
    "city": "Denver",
    "state": "CO",
    "zip": "80229",
    "county": "Denver County",
    "latitude": 39.81451,
    "longitude": -105.034543,
    "bedrooms": 4,
    "bathrooms": 2.0,
    "square_feet": 1893,
    "lot_size": 0.89,
    "year_built": 2020,
    "garage_spaces": 3,
    "basement": true,
    "pool": false,
    "fireplace": false,
    "property_type": "Townhouse",
    "market_value": 275564,
    "tax_assessment": 210581,
    "insurance_value": 353500,
    "rental_estimate": 2617,
    "hoa_name": "Sunset Hills HOA",
    "hoa_monthly_fee": 321,
    "hoa_special_assessment": 0,
    "hoa_amenities": "Tennis Court, Walking Trails",
    "hoa_management": "XYZ HOA Services",
    "hvac_cost": 4350,
    "exterior_paint": 6645,
    "interior_paint": 4997,
    "roof_repair": 18948,
    "plumbing_work": 1759,
    "data_source": "Sample Generator",
    "created_date": "2025-08-20T16:46:16.975249",
    "property_id": "PROP_117887"
  },
  {
    "address": "3618 Oak Ave",
    "city": "Houston",
    "state": "TX",
    "zip": "77053",
    "county": "Houston County",
    "latitude": 29.728775,
    "longitude": -95.408621,
    "bedrooms": 3,
    "bathrooms": 1.5,
    "square_feet": 1961,
    "lot_size": 0.8,
    "year_built": 2004,
    "garage_spaces": 0,
    "basement": true,
    "pool": false,
    "fireplace": false,
    "property_type": "Duplex",
    "market_value": 374719,
    "tax_assessment": 268345,
    "insurance_value": 445878,
    "rental_estimate": 4488,
    "hoa_name": "Oak Ridge Community",
    "hoa_monthly_fee": 58,
    "hoa_special_assessment": 0,
    "hoa_amenities": "Pool, Gym, Tennis Court",
    "hoa_management": "XYZ HOA Services",
    "plumbing_work": 3072,
    "flooring_cost": 5776,
    "data_source": "Sample Generator",
    "created_date": "2025-08-20T16:46:16.975281",
    "property_id": "PROP_416169"
  },
  {
    "address": "7863 Sunset Blvd",
    "city": "Charlotte",
    "state": "NC",
    "zip": "28249",
    "county": "Charlotte County",
    "latitude": 35.254887,
    "longitude": -80.883588,
    "bedrooms": 4,
    "bathrooms": 3.5,
    "square_feet": 1811,
    "lot_size": 0.91,
    "year_built": 2017,
    "garage_spaces": 0,
    "basement": false,
    "pool": false,
    "fireplace": false,
    "property_type": "Duplex",
    "market_value": 477383,
    "tax_assessment": 384949,
    "insurance_value": 577640,
    "rental_estimate": 5522,
    "bathroom_rehab": 7969,
    "plumbing_work": 4539,
    "kitchen_rehab": 22194,
    "exterior_paint": 4654,
    "data_source": "Sample Generator",
    "created_date": "2025-08-20T16:46:16.975308",
    "property_id": "PROP_841668"
  },
  {
    "address": "2866 Third St",
    "city": "Charlotte",
    "state": "NC",
    "zip": "28215",
    "county": "Charlotte County",
    "latitude": 35.173217,
    "longitude": -80.903842,
    "bedrooms": 3,
    "bathrooms": 1.0,
    "square_feet": 1590,
    "lot_size": 1.11,
    "year_built": 1992,
    "garage_spaces": 3,
    "basement": false,
    "pool": false,
    "fireplace": true,
    "property_type": "Condo",
    "market_value": 316281,
    "tax_assessment": 266942,
    "insurance_value": 404778,
    "rental_estimate": 3771,
    "hvac_cost": 9893,
    "interior_paint": 3824,
    "data_source": "Sample Generator",
    "created_date": "2025-08-20T16:46:16.975334",
    "property_id": "PROP_339163"
  },
  {
    "address": "3357 Sunset Blvd",
    "city": "Atlanta",
    "state": "GA",
    "zip": "30369",
    "county": "Atlanta County",
    "latitude": 33.750267,
    "longitude": -84.396048,
    "bedrooms": 4,
    "bathrooms": 4.0,
    "square_feet": 1944,
    "lot_size": 0.88,
    "year_built": 1998,
    "garage_spaces": 2,
    "basement": true,
    "pool": false,
    "fireplace": false,
    "property_type": "Condo",
    "market_value": 379707,
    "tax_assessment": 279746,
    "insurance_value": 487184,
    "rental_estimate": 3597,
    "exterior_paint": 7025,
    "hvac_cost": 5402,
    "data_source": "Sample Generator",
    "created_date": "2025-08-20T16:46:16.975358",
    "property_id": "PROP_223646"
  },
  {
    "address": "9116 Highland Dr",
    "city": "Houston",
    "state": "TX",
    "zip": "77055",
    "county": "Houston County",
    "latitude": 29.727517,
    "longitude": -95.334976,
    "bedrooms": 3,
    "bathrooms": 1.5,
    "square_feet": 1833,
    "lot_size": 0.11,
    "year_built": 2022,
    "garage_spaces": 1,
    "basement": true,
    "pool": false,
    "fireplace": false,
    "property_type": "Townhouse",
    "market_value": 574614,
    "tax_assessment": 431639,
    "insurance_value": 654451,
    "rental_estimate": 3897,
    "hoa_name": "Maple Grove HOA",
    "hoa_monthly_fee": 82,
    "hoa_special_assessment": 0,
    "hoa_amenities": "Playground, Clubhouse",
    "hoa_management": "ABC Property Management",
    "exterior_paint": 4202,
    "flooring_cost": 8484,
    "interior_paint": 2213,
    "plumbing_work": 1997,
    "data_source": "Sample Generator",
    "created_date": "2025-08-20T16:46:16.975388",
    "property_id": "PROP_806864"
  },
  {
    "address": "3275 Valley Dr",
    "city": "Atlanta",
    "state": "GA",
    "zip": "30311",
    "county": "Atlanta County",
    "latitude": 33.701026,
    "longitude": -84.465465,
    "bedrooms": 3,
    "bathrooms": 1.0,
    "square_feet": 1924,
    "lot_size": 0.27,
    "year_built": 1990,
    "garage_spaces": 0,
    "basement": false,
    "pool": false,
    "fireplace": false,
    "property_type": "Townhouse",
    "market_value": 366124,
    "tax_assessment": 324612,
    "insurance_value": 417186,
    "rental_estimate": 3586,
    "interior_paint": 2674,
    "electrical_work": 2745,
    "bathroom_rehab": 6673,
    "roof_repair": 17508,
    "kitchen_rehab": 12800,
    "data_source": "Sample Generator",
    "created_date": "2025-08-20T16:46:16.975416",
    "property_id": "PROP_929974"
  },
  {
    "address": "1469 River Rd",
    "city": "Atlanta",
    "state": "GA",
    "zip": "30337",
    "county": "Atlanta County",
    "latitude": 33.774894,
    "longitude": -84.298427,
    "bedrooms": 4,
    "bathrooms": 1.5,
    "square_feet": 2311,
    "lot_size": 0.65,
    "year_built": 1985,
    "garage_spaces": 2,
    "basement": true,
    "pool": false,
    "fireplace": false,
    "property_type": "Duplex",
    "market_value": 206504,
    "tax_assessment": 152077,
    "insurance_value": 259808,
    "rental_estimate": 1433,
    "hvac_cost": 11847,
    "electrical_work": 6086,
    "exterior_paint": 6451,
    "bathroom_rehab": 4424,
    "data_source": "Sample Generator",
    "created_date": "2025-08-20T16:46:16.975446",
    "property_id": "PROP_248535"
  },
  {
    "address": "1008 Second St",
    "city": "Houston",
    "state": "TX",
    "zip": "77089",
    "county": "Houston County",
    "latitude": 29.8364,
    "longitude": -95.410503,
    "bedrooms": 3,
    "bathrooms": 4.0,
    "square_feet": 1724,
    "lot_size": 0.14,
    "year_built": 1994,
    "garage_spaces": 0,
    "basement": true,
    "pool": false,
    "fireplace": false,
    "property_type": "Townhouse",
    "market_value": 447505,
    "tax_assessment": 322909,
    "insurance_value": 518607,
    "rental_estimate": 3953,
    "plumbing_work": 5415,
    "bathroom_rehab": 4822,
    "data_source": "Sample Generator",
    "created_date": "2025-08-20T16:46:16.975472",
    "property_id": "PROP_784357"
  },
  {
    "address": "2640 Maple Way",
    "city": "Nashville",
    "state": "TN",
    "zip": "37272",
    "county": "Nashville County",
    "latitude": 36.10841,
    "longitude": -86.733667,
    "bedrooms": 2,
    "bathrooms": 2.0,
    "square_feet": 1340,
    "lot_size": 0.49,
    "year_built": 1994,
    "garage_spaces": 1,
    "basement": true,
    "pool": false,
    "fireplace": true,
    "property_type": "Duplex",
    "market_value": 237904,
    "tax_assessment": 179369,
    "insurance_value": 263015,
    "rental_estimate": 1933,
    "hoa_name": "Pine Valley Association",
    "hoa_monthly_fee": 438,
    "hoa_special_assessment": 0,
    "hoa_amenities": "Pool, Spa",
    "hoa_management": "Premier HOA Solutions",
    "interior_paint": 2092,
    "bathroom_rehab": 10364,
    "kitchen_rehab": 9847,
    "roof_repair": 12547,
    "data_source": "Sample Generator",
    "created_date": "2025-08-20T16:46:16.975501",
    "property_id": "PROP_787972"
  },
  {
    "address": "5671 Sunset Blvd",
    "city": "Phoenix",
    "state": "AZ",
    "zip": "85059",
    "county": "Phoenix County",
    "latitude": 33.475769,
    "longitude": -112.052175,
    "bedrooms": 5,
    "bathrooms": 3.0,
    "square_feet": 2126,
    "lot_size": 0.74,
    "year_built": 1984,
    "garage_spaces": 1,
    "basement": false,
    "pool": false,
    "fireplace": false,
    "property_type": "Condo",
    "market_value": 462993,
    "tax_assessment": 384131,
    "insurance_value": 522037,
    "rental_estimate": 3569,
    "hvac_cost": 11187,
    "roof_repair": 14548,
    "exterior_paint": 3287,
    "interior_paint": 1825,
    "kitchen_rehab": 12213,
    "data_source": "Sample Generator",
    "created_date": "2025-08-20T16:46:16.975529",
    "property_id": "PROP_440375"
  },
  {
    "address": "9387 Maple Way",
    "city": "Charlotte",
    "state": "NC",
    "zip": "28290",
    "county": "Charlotte County",
    "latitude": 35.256137,
    "longitude": -80.864296,
    "bedrooms": 6,
    "bathrooms": 1.5,
    "square_feet": 2546,
    "lot_size": 0.78,
    "year_built": 1988,
    "garage_spaces": 0,
    "basement": true,
    "pool": false,
    "fireplace": true,
    "property_type": "Duplex",
    "market_value": 577778,
    "tax_assessment": 515476,
    "insurance_value": 737773,
    "rental_estimate": 2898,
    "plumbing_work": 5337,
    "roof_repair": 13947,
    "flooring_cost": 9678,
    "electrical_work": 3319,
    "data_source": "Sample Generator",
    "created_date": "2025-08-20T16:46:16.975559",
    "property_id": "PROP_245360"
  },
  {
    "address": "8119 Second St",
    "city": "Austin",
    "state": "TX",
    "zip": "78790",
    "county": "Austin County",
    "latitude": 30.190418,
    "longitude": -97.791281,
    "bedrooms": 3,
    "bathrooms": 3.5,
    "square_feet": 1434,
    "lot_size": 1.08,
    "year_built": 1998,
    "garage_spaces": 3,
    "basement": false,
    "pool": false,
    "fireplace": false,
    "property_type": "Multi-Family",
    "market_value": 376643,
    "tax_assessment": 275404,
    "insurance_value": 481047,
    "rental_estimate": 2315,
    "hvac_cost": 5357,
    "interior_paint": 1071,
    "exterior_paint": 6507,
    "bathroom_rehab": 11898,
    "data_source": "Sample Generator",
    "created_date": "2025-08-20T16:46:16.975586",
    "property_id": "PROP_504283"
  },
  {
    "address": "8206 Park Ave",
    "city": "Nashville",
    "state": "TN",
    "zip": "37256",
    "county": "Nashville County",
    "latitude": 36.196886,
    "longitude": -86.778185,
    "bedrooms": 4,
    "bathrooms": 1.0,
    "square_feet": 1620,
    "lot_size": 0.33,
    "year_built": 1997,
    "garage_spaces": 0,
    "basement": true,
    "pool": false,
    "fireplace": false,
    "property_type": "Townhouse",
    "market_value": 357167,
    "tax_assessment": 261596,
    "insurance_value": 435015,
    "rental_estimate": 2209,
    "bathroom_rehab": 3622,
    "kitchen_rehab": 13501,
    "interior_paint": 4490,
    "hvac_cost": 5155,
    "data_source": "Sample Generator",
    "created_date": "2025-08-20T16:46:16.975611",
    "property_id": "PROP_793986"
  },
  {
    "address": "7269 Oak Ave",
    "city": "Dallas",
    "state": "TX",
    "zip": "75201",
    "county": "Dallas County",
    "latitude": 32.754154,
    "longitude": -96.782678,
    "bedrooms": 5,
    "bathrooms": 1.0,
    "square_feet": 2635,
    "lot_size": 1.91,
    "year_built": 1993,
    "garage_spaces": 0,
    "basement": false,
    "pool": false,
    "fireplace": false,
    "property_type": "Townhouse",
    "market_value": 281603,
    "tax_assessment": 202763,
    "insurance_value": 364639,
    "rental_estimate": 3251,
    "kitchen_rehab": 11091,
    "exterior_paint": 2988,
    "roof_repair": 15838,
    "interior_paint": 3722,
    "bathroom_rehab": 10203,
    "data_source": "Sample Generator",
    "created_date": "2025-08-20T16:46:16.975640",
    "property_id": "PROP_183418"
  },
  {
    "address": "664 First St",
    "city": "Dallas",
    "state": "TX",
    "zip": "75265",
    "county": "Dallas County",
    "latitude": 32.719039,
    "longitude": -96.842099,
    "bedrooms": 3,
    "bathrooms": 2.0,
    "square_feet": 1622,
    "lot_size": 1.98,
    "year_built": 1992,
    "garage_spaces": 2,
    "basement": true,
    "pool": false,
    "fireplace": false,
    "property_type": "Duplex",
    "market_value": 461722,
    "tax_assessment": 379720,
    "insurance_value": 577503,
    "rental_estimate": 4002,
    "exterior_paint": 4488,
    "electrical_work": 5564,
    "interior_paint": 3532,
    "kitchen_rehab": 10761,
    "hvac_cost": 6427,
    "data_source": "Sample Generator",
    "created_date": "2025-08-20T16:46:16.975668",
    "property_id": "PROP_764561"
  },
  {
    "address": "5315 Valley Dr",
    "city": "Denver",
    "state": "CO",
    "zip": "80246",
    "county": "Denver County",
    "latitude": 39.652462,
    "longitude": -104.937024,
    "bedrooms": 4,
    "bathrooms": 1.0,
    "square_feet": 2212,
    "lot_size": 1.35,
    "year_built": 1979,
    "garage_spaces": 2,
    "basement": false,
    "pool": false,
    "fireplace": false,
    "property_type": "Single Family",
    "market_value": 532208,
    "tax_assessment": 429762,
    "insurance_value": 630871,
    "rental_estimate": 6070,
    "hoa_name": "Riverside HOA",
    "hoa_monthly_fee": 345,
    "hoa_special_assessment": 0,
    "hoa_amenities": "Clubhouse, Pool, Gym",
    "hoa_management": "XYZ HOA Services",
    "flooring_cost": 3296,
    "electrical_work": 6348,
    "exterior_paint": 5364,
    "data_source": "Sample Generator",
    "created_date": "2025-08-20T16:46:16.975697",
    "property_id": "PROP_612154"
  },
  {
    "address": "8346 Main St",
    "city": "Charlotte",
    "state": "NC",
    "zip": "28281",
    "county": "Charlotte County",
    "latitude": 35.255504,
    "longitude": -80.803082,
    "bedrooms": 5,
    "bathrooms": 3.0,
    "square_feet": 2765,
    "lot_size": 1.39,
    "year_built": 1989,
    "garage_spaces": 1,
    "basement": true,
    "pool": false,
    "fireplace": false,
    "property_type": "Single Family",
    "market_value": 484311,
    "tax_assessment": 406578,
    "insurance_value": 601198,
    "rental_estimate": 3541,
    "plumbing_work": 3950,
    "kitchen_rehab": 14920,
    "data_source": "Sample Generator",
    "created_date": "2025-08-20T16:46:16.975721",
    "property_id": "PROP_351889"
  },
  {
    "address": "1270 Park Ave",
    "city": "Charlotte",
    "state": "NC",
    "zip": "28284",
    "county": "Charlotte County",
    "latitude": 35.187539,
    "longitude": -80.832389,
    "bedrooms": 3,
    "bathrooms": 3.5,
    "square_feet": 1400,
    "lot_size": 0.91,
    "year_built": 1985,
    "garage_spaces": 2,
    "basement": false,
    "pool": true,
    "fireplace": false,
    "property_type": "Duplex",
    "market_value": 165894,
    "tax_assessment": 139792,
    "insurance_value": 200532,
    "rental_estimate": 1298,
    "hvac_cost": 7027,
    "electrical_work": 7058,
    "data_source": "Sample Generator",
    "created_date": "2025-08-20T16:46:16.975745",
    "property_id": "PROP_775959"
  },
  {
    "address": "4285 Valley Dr",
    "city": "Atlanta",
    "state": "GA",
    "zip": "30391",
    "county": "Atlanta County",
    "latitude": 33.747663,
    "longitude": -84.459515,
    "bedrooms": 3,
    "bathrooms": 1.5,
    "square_feet": 1538,
    "lot_size": 0.24,
    "year_built": 1994,
    "garage_spaces": 0,
    "basement": true,
    "pool": false,
    "fireplace": false,
    "property_type": "Townhouse",
    "market_value": 350530,
    "tax_assessment": 313346,
    "insurance_value": 451805,
    "rental_estimate": 2539,
    "hvac_cost": 6139,
    "roof_repair": 19497,
    "plumbing_work": 5182,
    "kitchen_rehab": 18886,
    "data_source": "Sample Generator",
    "created_date": "2025-08-20T16:46:16.975771",
    "property_id": "PROP_634293"
  },
  {
    "address": "4731 Elm St",
    "city": "Austin",
    "state": "TX",
    "zip": "78735",
    "county": "Austin County",
    "latitude": 30.215375,
    "longitude": -97.685636,
    "bedrooms": 3,
    "bathrooms": 4.0,
    "square_feet": 1630,
    "lot_size": 1.98,
    "year_built": 2022,
    "garage_spaces": 3,
    "basement": true,
    "pool": false,
    "fireplace": true,
    "property_type": "Townhouse",
    "market_value": 537676,
    "tax_assessment": 468088,
    "insurance_value": 658808,
    "rental_estimate": 6098,
    "exterior_paint": 5756,
    "bathroom_rehab": 8282,
    "roof_repair": 8275,
    "data_source": "Sample Generator",
    "created_date": "2025-08-20T16:46:16.975797",
    "property_id": "PROP_715535"
  },
  {
    "address": "626 River Rd",
    "city": "Dallas",
    "state": "TX",
    "zip": "75227",
    "county": "Dallas County",
    "latitude": 32.70322,
    "longitude": -96.780717,
    "bedrooms": 4,
    "bathrooms": 3.0,
    "square_feet": 2284,
    "lot_size": 0.28,
    "year_built": 1995,
    "garage_spaces": 3,
    "basement": true,
    "pool": false,
    "fireplace": false,
    "property_type": "Duplex",
    "market_value": 524320,
    "tax_assessment": 466153,
    "insurance_value": 587628,
    "rental_estimate": 3626,
    "hoa_name": "Maple Grove HOA",
    "hoa_monthly_fee": 100,
    "hoa_special_assessment": 0,
    "hoa_amenities": "Pool, Spa",
    "hoa_management": "ABC Property Management",
    "exterior_paint": 7369,
    "bathroom_rehab": 7096,
    "electrical_work": 2418,
    "interior_paint": 3668,
    "plumbing_work": 2909,
    "data_source": "Sample Generator",
    "created_date": "2025-08-20T16:46:16.975831",
    "property_id": "PROP_229917"
  },
  {
    "address": "5169 Hill St",
    "city": "Dallas",
    "state": "TX",
    "zip": "75236",
    "county": "Dallas County",
    "latitude": 32.70404,
    "longitude": -96.708113,
    "bedrooms": 3,
    "bathrooms": 2.0,
    "square_feet": 1883,
    "lot_size": 1.47,
    "year_built": 2022,
    "garage_spaces": 3,
    "basement": true,
    "pool": false,
    "fireplace": false,
    "property_type": "Single Family",
    "market_value": 704213,
    "tax_assessment": 564894,
    "insurance_value": 776409,
    "rental_estimate": 3628,
    "hoa_name": "Oak Ridge Community",
    "hoa_monthly_fee": 406,
    "hoa_special_assessment": 0,
    "hoa_amenities": "Pool, Gym, Tennis Court",
    "hoa_management": "XYZ HOA Services",
    "plumbing_work": 3629,
    "hvac_cost": 10670,
    "data_source": "Sample Generator",
    "created_date": "2025-08-20T16:46:16.975857",
    "property_id": "PROP_520005"
  },
  {
    "address": "8885 First St",
    "city": "Austin",
    "state": "TX",
    "zip": "78784",
    "county": "Austin County",
    "latitude": 30.305969,
    "longitude": -97.717105,
    "bedrooms": 4,
    "bathrooms": 2.5,
    "square_feet": 1626,
    "lot_size": 1.11,
    "year_built": 1997,
    "garage_spaces": 1,
    "basement": false,
    "pool": false,
    "fireplace": false,
    "property_type": "Condo",
    "market_value": 313347,
    "tax_assessment": 272324,
    "insurance_value": 353064,
    "rental_estimate": 2640,
    "exterior_paint": 5829,
    "interior_paint": 3620,
    "electrical_work": 3370,
    "bathroom_rehab": 9921,
    "data_source": "Sample Generator",
    "created_date": "2025-08-20T16:46:16.975883",
    "property_id": "PROP_444910"
  },
  {
    "address": "2578 Maple Way",
    "city": "Charlotte",
    "state": "NC",
    "zip": "28291",
    "county": "Charlotte County",
    "latitude": 35.224844,
    "longitude": -80.937447,
    "bedrooms": 4,
    "bathrooms": 1.0,
    "square_feet": 2278,
    "lot_size": 0.15,
    "year_built": 1988,
    "garage_spaces": 1,
    "basement": true,
    "pool": false,
    "fireplace": false,
    "property_type": "Townhouse",
    "market_value": 402505,
    "tax_assessment": 287794,
    "insurance_value": 465469,
    "rental_estimate": 4517,
    "hoa_name": "Pine Valley Association",
    "hoa_monthly_fee": 349,
    "hoa_special_assessment": 0,
    "hoa_amenities": "Clubhouse, Pool, Gym",
    "hoa_management": "Community First Management",
    "flooring_cost": 10434,
    "roof_repair": 11966,
    "electrical_work": 4747,
    "data_source": "Sample Generator",
    "created_date": "2025-08-20T16:46:16.975912",
    "property_id": "PROP_848525"
  },
  {
    "address": "5959 Elm St",
    "city": "Charlotte",
    "state": "NC",
    "zip": "28239",
    "county": "Charlotte County",
    "latitude": 35.162543,
    "longitude": -80.913501,
    "bedrooms": 4,
    "bathrooms": 1.0,
    "square_feet": 2056,
    "lot_size": 1.64,
    "year_built": 1984,
    "garage_spaces": 1,
    "basement": false,
    "pool": false,
    "fireplace": false,
    "property_type": "Multi-Family",
    "market_value": 239737,
    "tax_assessment": 177728,
    "insurance_value": 302741,
    "rental_estimate": 2533,
    "kitchen_rehab": 19629,
    "bathroom_rehab": 5393,
    "data_source": "Sample Generator",
    "created_date": "2025-08-20T16:46:16.975939",
    "property_id": "PROP_959021"
  },
  {
    "address": "3514 Hill St",
    "city": "Denver",
    "state": "CO",
    "zip": "80292",
    "county": "Denver County",
    "latitude": 39.701629,
    "longitude": -104.896996,
    "bedrooms": 3,
    "bathrooms": 1.0,
    "square_feet": 1914,
    "lot_size": 0.45,
    "year_built": 2001,
    "garage_spaces": 2,
    "basement": false,
    "pool": true,
    "fireplace": false,
    "property_type": "Duplex",
    "market_value": 331116,
    "tax_assessment": 254312,
    "insurance_value": 379952,
    "rental_estimate": 1690,
    "plumbing_work": 3335,
    "kitchen_rehab": 17217,
    "data_source": "Sample Generator",
    "created_date": "2025-08-20T16:46:16.975964",
    "property_id": "PROP_145843"
  },
  {
    "address": "6359 First St",
    "city": "Austin",
    "state": "TX",
    "zip": "78786",
    "county": "Austin County",
    "latitude": 30.262488,
    "longitude": -97.69515,
    "bedrooms": 5,
    "bathrooms": 1.0,
    "square_feet": 2350,
    "lot_size": 1.0,
    "year_built": 1981,
    "garage_spaces": 1,
    "basement": true,
    "pool": true,
    "fireplace": false,
    "property_type": "Condo",
    "market_value": 525493,
    "tax_assessment": 444724,
    "insurance_value": 593761,
    "rental_estimate": 3000,
    "interior_paint": 4074,
    "roof_repair": 12295,
    "plumbing_work": 1984,
    "data_source": "Sample Generator",
    "created_date": "2025-08-20T16:46:16.975990",
    "property_id": "PROP_609659"
  },
  {
    "address": "241 Maple Way",
    "city": "Atlanta",
    "state": "GA",
    "zip": "30311",
    "county": "Atlanta County",
    "latitude": 33.766434,
    "longitude": -84.36302,
    "bedrooms": 3,
    "bathrooms": 3.5,
    "square_feet": 1283,
    "lot_size": 0.87,
    "year_built": 2023,
    "garage_spaces": 3,
    "basement": true,
    "pool": true,
    "fireplace": false,
    "property_type": "Duplex",
    "market_value": 400168,
    "tax_assessment": 345412,
    "insurance_value": 452729,
    "rental_estimate": 2026,
    "hoa_name": "Riverside HOA",
    "hoa_monthly_fee": 163,
    "hoa_special_assessment": 0,
    "hoa_amenities": "Clubhouse, Pool, Gym",
    "hoa_management": "XYZ HOA Services",
    "exterior_paint": 3259,
    "bathroom_rehab": 9753,
    "electrical_work": 6707,
    "plumbing_work": 2418,
    "roof_repair": 15016,
    "data_source": "Sample Generator",
    "created_date": "2025-08-20T16:46:16.976021",
    "property_id": "PROP_498267"
  },
  {
    "address": "1762 Maple Way",
    "city": "Austin",
    "state": "TX",
    "zip": "78706",
    "county": "Austin County",
    "latitude": 30.182313,
    "longitude": -97.802052,
    "bedrooms": 3,
    "bathrooms": 3.5,
    "square_feet": 1502,
    "lot_size": 1.09,
    "year_built": 2006,
    "garage_spaces": 2,
    "basement": false,
    "pool": false,
    "fireplace": true,
    "property_type": "Townhouse",
    "market_value": 416292,
    "tax_assessment": 318754,
    "insurance_value": 505073,
    "rental_estimate": 3484,
    "hoa_name": "Oak Ridge Community",
    "hoa_monthly_fee": 236,
    "hoa_special_assessment": 0,
    "hoa_amenities": "Playground, Clubhouse",
    "hoa_management": "Community First Management",
    "plumbing_work": 5841,
    "flooring_cost": 7027,
    "kitchen_rehab": 24460,
    "bathroom_rehab": 6782,
    "roof_repair": 10678,
    "data_source": "Sample Generator",
    "created_date": "2025-08-20T16:46:16.976052",
    "property_id": "PROP_497185"
  },
  {
    "address": "7182 Highland Dr",
    "city": "Atlanta",
    "state": "GA",
    "zip": "30334",
    "county": "Atlanta County",
    "latitude": 33.676755,
    "longitude": -84.357208,
    "bedrooms": 3,
    "bathrooms": 1.0,
    "square_feet": 1444,
    "lot_size": 1.5,
    "year_built": 2001,
    "garage_spaces": 2,
    "basement": false,
    "pool": false,
    "fireplace": true,
    "property_type": "Single Family",
    "market_value": 289788,
    "tax_assessment": 249691,
    "insurance_value": 328339,
    "rental_estimate": 1794,
    "plumbing_work": 5687,
    "kitchen_rehab": 12905,
    "data_source": "Sample Generator",
    "created_date": "2025-08-20T16:46:16.976076",
    "property_id": "PROP_233394"
  },
  {
    "address": "5011 Pine Dr",
    "city": "Austin",
    "state": "TX",
    "zip": "78717",
    "county": "Austin County",
    "latitude": 30.354885,
    "longitude": -97.785912,
    "bedrooms": 3,
    "bathrooms": 1.0,
    "square_feet": 1210,
    "lot_size": 1.9,
    "year_built": 2006,
    "garage_spaces": 3,
    "basement": true,
    "pool": true,
    "fireplace": false,
    "property_type": "Condo",
    "market_value": 203457,
    "tax_assessment": 149986,
    "insurance_value": 256124,
    "rental_estimate": 1097,
    "interior_paint": 3079,
    "roof_repair": 8225,
    "exterior_paint": 4503,
    "hvac_cost": 7145,
    "bathroom_rehab": 10601,
    "data_source": "Sample Generator",
    "created_date": "2025-08-20T16:46:16.976108",
    "property_id": "PROP_801947"
  },
  {
    "address": "6456 Pine Dr",
    "city": "Atlanta",
    "state": "GA",
    "zip": "30391",
    "county": "Atlanta County",
    "latitude": 33.784123,
    "longitude": -84.469416,
    "bedrooms": 4,
    "bathrooms": 2.5,
    "square_feet": 2225,
    "lot_size": 0.1,
    "year_built": 2007,
    "garage_spaces": 1,
    "basement": true,
    "pool": false,
    "fireplace": false,
    "property_type": "Townhouse",
    "market_value": 332510,
    "tax_assessment": 242724,
    "insurance_value": 421142,
    "rental_estimate": 3862,
    "roof_repair": 14716,
    "kitchen_rehab": 24806,
    "plumbing_work": 4286,
    "bathroom_rehab": 11333,
    "data_source": "Sample Generator",
    "created_date": "2025-08-20T16:46:16.976135",
    "property_id": "PROP_209667"
  },
  {
    "address": "6085 Sunset Blvd",
    "city": "Nashville",
    "state": "TN",
    "zip": "37253",
    "county": "Nashville County",
    "latitude": 36.11962,
    "longitude": -86.693661,
    "bedrooms": 3,
    "bathrooms": 2.5,
    "square_feet": 1394,
    "lot_size": 0.7,
    "year_built": 2001,
    "garage_spaces": 1,
    "basement": true,
    "pool": true,
    "fireplace": false,
    "property_type": "Multi-Family",
    "market_value": 309827,
    "tax_assessment": 221241,
    "insurance_value": 374578,
    "rental_estimate": 1824,
    "exterior_paint": 6443,
    "electrical_work": 3023,
    "plumbing_work": 2434,
    "data_source": "Sample Generator",
    "created_date": "2025-08-20T16:46:16.976162",
    "property_id": "PROP_717142"
  },
  {
    "address": "6638 River Rd",
    "city": "Nashville",
    "state": "TN",
    "zip": "37297",
    "county": "Nashville County",
    "latitude": 36.241284,
    "longitude": -86.758704,
    "bedrooms": 2,
    "bathrooms": 1.5,
    "square_feet": 1349,
    "lot_size": 0.14,
    "year_built": 1981,
    "garage_spaces": 2,
    "basement": true,
    "pool": false,
    "fireplace": true,
    "property_type": "Condo",
    "market_value": 262491,
    "tax_assessment": 195471,
    "insurance_value": 334622,
    "rental_estimate": 1589,
    "roof_repair": 9340,
    "plumbing_work": 4822,
    "data_source": "Sample Generator",
    "created_date": "2025-08-20T16:46:16.976187",
    "property_id": "PROP_265818"
  },
  {
    "address": "6066 Third St",
    "city": "Atlanta",
    "state": "GA",
    "zip": "30340",
    "county": "Atlanta County",
    "latitude": 33.82439,
    "longitude": -84.389731,
    "bedrooms": 3,
    "bathrooms": 3.0,
    "square_feet": 1668,
    "lot_size": 1.77,
    "year_built": 1987,
    "garage_spaces": 2,
    "basement": false,
    "pool": false,
    "fireplace": false,
    "property_type": "Condo",
    "market_value": 232217,
    "tax_assessment": 199111,
    "insurance_value": 286110,
    "rental_estimate": 2684,
    "hoa_name": "Maple Grove HOA",
    "hoa_monthly_fee": 381,
    "hoa_special_assessment": 0,
    "hoa_amenities": "Pool, Gym, Tennis Court",
    "hoa_management": "Community First Management",
    "flooring_cost": 6257,
    "bathroom_rehab": 10545,
    "kitchen_rehab": 14170,
    "data_source": "Sample Generator",
    "created_date": "2025-08-20T16:46:16.976217",
    "property_id": "PROP_811067"
  },
  {
    "address": "6457 First St",
    "city": "Austin",
    "state": "TX",
    "zip": "78730",
    "county": "Austin County",
    "latitude": 30.272301,
    "longitude": -97.661451,
    "bedrooms": 3,
    "bathrooms": 2.0,
    "square_feet": 1790,
    "lot_size": 0.45,
    "year_built": 2016,
    "garage_spaces": 3,
    "basement": false,
    "pool": true,
    "fireplace": false,
    "property_type": "Townhouse",
    "market_value": 594455,
    "tax_assessment": 519936,
    "insurance_value": 675887,
    "rental_estimate": 5194,
    "hoa_name": "Cedar Creek Community",
    "hoa_monthly_fee": 111,
    "hoa_special_assessment": 0,
    "hoa_amenities": "Pool, Gym, Tennis Court",
    "hoa_management": "XYZ HOA Services",
    "bathroom_rehab": 4031,
    "exterior_paint": 7000,
    "electrical_work": 7620,
    "roof_repair": 13317,
    "data_source": "Sample Generator",
    "created_date": "2025-08-20T16:46:16.976247",
    "property_id": "PROP_185248"
  },
  {
    "address": "6841 Highland Dr",
    "city": "Phoenix",
    "state": "AZ",
    "zip": "85048",
    "county": "Phoenix County",
    "latitude": 33.397043,
    "longitude": -112.100264,
    "bedrooms": 5,
    "bathrooms": 3.0,
    "square_feet": 2695,
    "lot_size": 0.64,
    "year_built": 2023,
    "garage_spaces": 2,
    "basement": true,
    "pool": false,
    "fireplace": false,
    "property_type": "Single Family",
    "market_value": 572272,
    "tax_assessment": 463085,
    "insurance_value": 705874,
    "rental_estimate": 3765,
    "kitchen_rehab": 20801,
    "bathroom_rehab": 11118,
    "interior_paint": 1905,
    "electrical_work": 6663,
    "data_source": "Sample Generator",
    "created_date": "2025-08-20T16:46:16.976275",
    "property_id": "PROP_755690"
  },
  {
    "address": "106 Maple Way",
    "city": "Houston",
    "state": "TX",
    "zip": "77019",
    "county": "Houston County",
    "latitude": 29.811886,
    "longitude": -95.301448,
    "bedrooms": 3,
    "bathrooms": 1.5,
    "square_feet": 1992,
    "lot_size": 0.36,
    "year_built": 2021,
    "garage_spaces": 1,
    "basement": false,
    "pool": false,
    "fireplace": true,
    "property_type": "Single Family",
    "market_value": 296008,
    "tax_assessment": 229755,
    "insurance_value": 326222,
    "rental_estimate": 3258,
    "hoa_name": "Sunset Hills HOA",
    "hoa_monthly_fee": 392,
    "hoa_special_assessment": 0,
    "hoa_amenities": "Pool, Spa",
    "hoa_management": "Premier HOA Solutions",
    "plumbing_work": 3232,
    "bathroom_rehab": 11782,
    "data_source": "Sample Generator",
    "created_date": "2025-08-20T16:46:16.976301",
    "property_id": "PROP_114108"
  },
  {
    "address": "1464 River Rd",
    "city": "Charlotte",
    "state": "NC",
    "zip": "28205",
    "county": "Charlotte County",
    "latitude": 35.287073,
    "longitude": -80.779167,
    "bedrooms": 4,
    "bathrooms": 2.0,
    "square_feet": 2371,
    "lot_size": 0.43,
    "year_built": 1983,
    "garage_spaces": 3,
    "basement": true,
    "pool": false,
    "fireplace": false,
    "property_type": "Multi-Family",
    "market_value": 406688,
    "tax_assessment": 351479,
    "insurance_value": 491404,
    "rental_estimate": 2639,
    "plumbing_work": 3234,
    "flooring_cost": 7021,
    "kitchen_rehab": 20975,
    "data_source": "Sample Generator",
    "created_date": "2025-08-20T16:46:16.976327",
    "property_id": "PROP_818446"
  },
  {
    "address": "156 Elm St",
    "city": "Austin",
    "state": "TX",
    "zip": "78720",
    "county": "Austin County",
    "latitude": 30.226019,
    "longitude": -97.70394,
    "bedrooms": 3,
    "bathrooms": 3.5,
    "square_feet": 1225,
    "lot_size": 1.04,
    "year_built": 1975,
    "garage_spaces": 0,
    "basement": false,
    "pool": false,
    "fireplace": true,
    "property_type": "Townhouse",
    "market_value": 330297,
    "tax_assessment": 278145,
    "insurance_value": 401692,
    "rental_estimate": 2133,
    "hoa_name": "Cedar Creek Community",
    "hoa_monthly_fee": 455,
    "hoa_special_assessment": 0,
    "hoa_amenities": "Pool, Spa",
    "hoa_management": "ABC Property Management",
    "hvac_cost": 7029,
    "electrical_work": 7795,
    "interior_paint": 2496,
    "kitchen_rehab": 9544,
    "roof_repair": 18089,
    "data_source": "Sample Generator",
    "created_date": "2025-08-20T16:46:16.976357",
    "property_id": "PROP_181808"
  },
  {
    "address": "2864 River Rd",
    "city": "Dallas",
    "state": "TX",
    "zip": "75226",
    "county": "Dallas County",
    "latitude": 32.747574,
    "longitude": -96.87651,
    "bedrooms": 3,
    "bathrooms": 1.0,
    "square_feet": 1221,
    "lot_size": 1.2,
    "year_built": 1985,
    "garage_spaces": 3,
    "basement": true,
    "pool": false,
    "fireplace": false,
    "property_type": "Townhouse",
    "market_value": 173727,
    "tax_assessment": 141520,
    "insurance_value": 205989,
    "rental_estimate": 1840,
    "kitchen_rehab": 9729,
    "flooring_cost": 5350,
    "hvac_cost": 7079,
    "electrical_work": 5991,
    "interior_paint": 1361,
    "data_source": "Sample Generator",
    "created_date": "2025-08-20T16:46:16.976388",
    "property_id": "PROP_611530"
  },
  {
    "address": "4672 Third St",
    "city": "Atlanta",
    "state": "GA",
    "zip": "30342",
    "county": "Atlanta County",
    "latitude": 33.660159,
    "longitude": -84.342388,
    "bedrooms": 3,
    "bathrooms": 2.0,
    "square_feet": 1681,
    "lot_size": 1.72,
    "year_built": 1994,
    "garage_spaces": 0,
    "basement": true,
    "pool": false,
    "fireplace": false,
    "property_type": "Single Family",
    "market_value": 285189,
    "tax_assessment": 223572,
    "insurance_value": 360855,
    "rental_estimate": 2026,
    "flooring_cost": 8526,
    "interior_paint": 2244,
    "plumbing_work": 2584,
    "data_source": "Sample Generator",
    "created_date": "2025-08-20T16:46:16.976414",
    "property_id": "PROP_951118"
  },
  {
    "address": "3532 Highland Dr",
    "city": "Houston",
    "state": "TX",
    "zip": "77023",
    "county": "Houston County",
    "latitude": 29.849014,
    "longitude": -95.4125,
    "bedrooms": 5,
    "bathrooms": 2.5,
    "square_feet": 2563,
    "lot_size": 1.04,
    "year_built": 2009,
    "garage_spaces": 0,
    "basement": false,
    "pool": false,
    "fireplace": false,
    "property_type": "Townhouse",
    "market_value": 447738,
    "tax_assessment": 318812,
    "insurance_value": 522311,
    "rental_estimate": 2949,
    "flooring_cost": 8286,
    "bathroom_rehab": 7710,
    "data_source": "Sample Generator",
    "created_date": "2025-08-20T16:46:16.976439",
    "property_id": "PROP_842744"
  },
  {
    "address": "4979 Park Ave",
    "city": "Charlotte",
    "state": "NC",
    "zip": "28296",
    "county": "Charlotte County",
    "latitude": 35.207173,
    "longitude": -80.805764,
    "bedrooms": 4,
    "bathrooms": 4.0,
    "square_feet": 1739,
    "lot_size": 0.6,
    "year_built": 2000,
    "garage_spaces": 3,
    "basement": false,
    "pool": false,
    "fireplace": true,
    "property_type": "Duplex",
    "market_value": 433670,
    "tax_assessment": 357133,
    "insurance_value": 558015,
    "rental_estimate": 4507,
    "roof_repair": 11353,
    "interior_paint": 1868,
    "data_source": "Sample Generator",
    "created_date": "2025-08-20T16:46:16.976465",
    "property_id": "PROP_181233"
  },
  {
    "address": "3503 Hill St",
    "city": "Houston",
    "state": "TX",
    "zip": "77062",
    "county": "Houston County",
    "latitude": 29.74449,
    "longitude": -95.381802,
    "bedrooms": 4,
    "bathrooms": 3.0,
    "square_feet": 1645,
    "lot_size": 1.89,
    "year_built": 1972,
    "garage_spaces": 3,
    "basement": false,
    "pool": false,
    "fireplace": false,
    "property_type": "Multi-Family",
    "market_value": 483655,
    "tax_assessment": 381318,
    "insurance_value": 556329,
    "rental_estimate": 5184,
    "hvac_cost": 11036,
    "exterior_paint": 4282,
    "data_source": "Sample Generator",
    "created_date": "2025-08-20T16:46:16.976488",
    "property_id": "PROP_426812"
  },
  {
    "address": "5174 First St",
    "city": "Nashville",
    "state": "TN",
    "zip": "37298",
    "county": "Nashville County",
    "latitude": 36.261647,
    "longitude": -86.744697,
    "bedrooms": 4,
    "bathrooms": 1.5,
    "square_feet": 2132,
    "lot_size": 1.31,
    "year_built": 2017,
    "garage_spaces": 1,
    "basement": true,
    "pool": false,
    "fireplace": false,
    "property_type": "Multi-Family",
    "market_value": 667569,
    "tax_assessment": 574050,
    "insurance_value": 816312,
    "rental_estimate": 6788,
    "hoa_name": "Riverside HOA",
    "hoa_monthly_fee": 461,
    "hoa_special_assessment": 0,
    "hoa_amenities": "Playground, Clubhouse",
    "hoa_management": "Community First Management",
    "kitchen_rehab": 18269,
    "flooring_cost": 5661,
    "interior_paint": 2146,
    "bathroom_rehab": 10043,
    "data_source": "Sample Generator",
    "created_date": "2025-08-20T16:46:16.976519",
    "property_id": "PROP_196645"
  },
  {
    "address": "9427 Main St",
    "city": "Atlanta",
    "state": "GA",
    "zip": "30362",
    "county": "Atlanta County",
    "latitude": 33.842679,
    "longitude": -84.486221,
    "bedrooms": 4,
    "bathrooms": 1.5,
    "square_feet": 2351,
    "lot_size": 1.28,
    "year_built": 1977,
    "garage_spaces": 1,
    "basement": true,
    "pool": true,
    "fireplace": false,
    "property_type": "Townhouse",
    "market_value": 432845,
    "tax_assessment": 335030,
    "insurance_value": 538495,
    "rental_estimate": 3899,
    "hoa_name": "Sunset Hills HOA",
    "hoa_monthly_fee": 230,
    "hoa_special_assessment": 0,
    "hoa_amenities": "Clubhouse, Pool, Gym",
    "hoa_management": "ABC Property Management",
    "hvac_cost": 11895,
    "kitchen_rehab": 8333,
    "plumbing_work": 3567,
    "bathroom_rehab": 13486,
    "data_source": "Sample Generator",
    "created_date": "2025-08-20T16:46:16.976550",
    "property_id": "PROP_587281"
  },
  {
    "address": "8500 Oak Ave",
    "city": "Dallas",
    "state": "TX",
    "zip": "75299",
    "county": "Dallas County",
    "latitude": 32.70561,
    "longitude": -96.756309,
    "bedrooms": 2,
    "bathrooms": 2.0,
    "square_feet": 1259,
    "lot_size": 1.53,
    "year_built": 2017,
    "garage_spaces": 0,
    "basement": true,
    "pool": true,
    "fireplace": false,
    "property_type": "Single Family",
    "market_value": 296408,
    "tax_assessment": 247162,
    "insurance_value": 377851,
    "rental_estimate": 3540,
    "kitchen_rehab": 18011,
    "electrical_work": 6100,
    "data_source": "Sample Generator",
    "created_date": "2025-08-20T16:46:16.976576",
    "property_id": "PROP_663981"
  },
  {
    "address": "1213 Highland Dr",
    "city": "Atlanta",
    "state": "GA",
    "zip": "30309",
    "county": "Atlanta County",
    "latitude": 33.702905,
    "longitude": -84.452446,
    "bedrooms": 5,
    "bathrooms": 2.0,
    "square_feet": 2635,
    "lot_size": 1.2,
    "year_built": 1989,
    "garage_spaces": 2,
    "basement": false,
    "pool": false,
    "fireplace": false,
    "property_type": "Townhouse",
    "market_value": 486516,
    "tax_assessment": 402531,
    "insurance_value": 597553,
    "rental_estimate": 3538,
    "hoa_name": "Pine Valley Association",
    "hoa_monthly_fee": 490,
    "hoa_special_assessment": 0,
    "hoa_amenities": "Clubhouse, Pool, Gym",
    "hoa_management": "ABC Property Management",
    "flooring_cost": 11136,
    "roof_repair": 8960,
    "bathroom_rehab": 6818,
    "interior_paint": 1221,
    "plumbing_work": 3737,
    "data_source": "Sample Generator",
    "created_date": "2025-08-20T16:46:16.976606",
    "property_id": "PROP_887984"
  },
  {
    "address": "2244 Maple Way",
    "city": "Atlanta",
    "state": "GA",
    "zip": "30358",
    "county": "Atlanta County",
    "latitude": 33.838345,
    "longitude": -84.448585,
    "bedrooms": 5,
    "bathrooms": 2.5,
    "square_feet": 2141,
    "lot_size": 0.92,
    "year_built": 2011,
    "garage_spaces": 0,
    "basement": true,
    "pool": false,
    "fireplace": false,
    "property_type": "Townhouse",
    "market_value": 708197,
    "tax_assessment": 535762,
    "insurance_value": 852610,
    "rental_estimate": 7144,
    "exterior_paint": 2089,
    "electrical_work": 2557,
    "kitchen_rehab": 24184,
    "data_source": "Sample Generator",
    "created_date": "2025-08-20T16:46:16.976631",
    "property_id": "PROP_914115"
  },
  {
    "address": "1164 Highland Dr",
    "city": "Denver",
    "state": "CO",
    "zip": "80276",
    "county": "Denver County",
    "latitude": 39.810623,
    "longitude": -105.053739,
    "bedrooms": 3,
    "bathrooms": 1.0,
    "square_feet": 1775,
    "lot_size": 0.86,
    "year_built": 1995,
    "garage_spaces": 3,
    "basement": false,
    "pool": false,
    "fireplace": false,
    "property_type": "Single Family",
    "market_value": 308715,
    "tax_assessment": 234243,
    "insurance_value": 382787,
    "rental_estimate": 2983,
    "hoa_name": "Maple Grove HOA",
    "hoa_monthly_fee": 371,
    "hoa_special_assessment": 0,
    "hoa_amenities": "Pool, Gym, Tennis Court",
    "hoa_management": "Community First Management",
    "plumbing_work": 3082,
    "electrical_work": 7215,
    "flooring_cost": 7177,
    "roof_repair": 19784,
    "bathroom_rehab": 8525,
    "data_source": "Sample Generator",
    "created_date": "2025-08-20T16:46:16.976665",
    "property_id": "PROP_661026"
  },
  {
    "address": "2002 Valley Dr",
    "city": "Charlotte",
    "state": "NC",
    "zip": "28226",
    "county": "Charlotte County",
    "latitude": 35.279835,
    "longitude": -80.896249,
    "bedrooms": 3,
    "bathrooms": 3.0,
    "square_feet": 1409,
    "lot_size": 1.7,
    "year_built": 2009,
    "garage_spaces": 3,
    "basement": true,
    "pool": false,
    "fireplace": false,
    "property_type": "Townhouse",
    "market_value": 302924,
    "tax_assessment": 237051,
    "insurance_value": 377706,
    "rental_estimate": 2067,
    "electrical_work": 4016,
    "bathroom_rehab": 12842,
    "data_source": "Sample Generator",
    "created_date": "2025-08-20T16:46:16.976690",
    "property_id": "PROP_550916"
  },
  {
    "address": "4582 Valley Dr",
    "city": "Houston",
    "state": "TX",
    "zip": "77047",
    "county": "Houston County",
    "latitude": 29.767854,
    "longitude": -95.312893,
    "bedrooms": 3,
    "bathrooms": 1.0,
    "square_feet": 1272,
    "lot_size": 1.39,
    "year_built": 2014,
    "garage_spaces": 2,
    "basement": true,
    "pool": false,
    "fireplace": false,
    "property_type": "Condo",
    "market_value": 274532,
    "tax_assessment": 219006,
    "insurance_value": 356208,
    "rental_estimate": 2603,
    "hoa_name": "Pine Valley Association",
    "hoa_monthly_fee": 446,
    "hoa_special_assessment": 0,
    "hoa_amenities": "Pool, Spa",
    "hoa_management": "Community First Management",
    "interior_paint": 3759,
    "kitchen_rehab": 24686,
    "exterior_paint": 5151,
    "hvac_cost": 10458,
    "data_source": "Sample Generator",
    "created_date": "2025-08-20T16:46:16.976719",
    "property_id": "PROP_868361"
  },
  {
    "address": "691 Park Ave",
    "city": "Phoenix",
    "state": "AZ",
    "zip": "85084",
    "county": "Phoenix County",
    "latitude": 33.446556,
    "longitude": -112.067627,
    "bedrooms": 3,
    "bathrooms": 3.5,
    "square_feet": 1992,
    "lot_size": 0.86,
    "year_built": 2019,
    "garage_spaces": 3,
    "basement": true,
    "pool": true,
    "fireplace": true,
    "property_type": "Condo",
    "market_value": 521114,
    "tax_assessment": 403867,
    "insurance_value": 600838,
    "rental_estimate": 3342,
    "hoa_name": "Cedar Creek Community",
    "hoa_monthly_fee": 382,
    "hoa_special_assessment": 0,
    "hoa_amenities": "Pool, Gym, Tennis Court",
    "hoa_management": "ABC Property Management",
    "electrical_work": 3593,
    "hvac_cost": 4203,
    "kitchen_rehab": 6464,
    "plumbing_work": 2251,
    "data_source": "Sample Generator",
    "created_date": "2025-08-20T16:46:16.976749",
    "property_id": "PROP_940559"
  },
  {
    "address": "332 Highland Dr",
    "city": "Atlanta",
    "state": "GA",
    "zip": "30376",
    "county": "Atlanta County",
    "latitude": 33.707822,
    "longitude": -84.307836,
    "bedrooms": 5,
    "bathrooms": 3.5,
    "square_feet": 2426,
    "lot_size": 0.59,
    "year_built": 1974,
    "garage_spaces": 1,
    "basement": false,
    "pool": false,
    "fireplace": false,
    "property_type": "Townhouse",
    "market_value": 462352,
    "tax_assessment": 374612,
    "insurance_value": 511321,
    "rental_estimate": 4043,
    "hoa_name": "Pine Valley Association",
    "hoa_monthly_fee": 105,
    "hoa_special_assessment": 0,
    "hoa_amenities": "Clubhouse, Pool, Gym",
    "hoa_management": "ABC Property Management",
    "hvac_cost": 6420,
    "electrical_work": 3391,
    "flooring_cost": 3231,
    "data_source": "Sample Generator",
    "created_date": "2025-08-20T16:46:16.976776",
    "property_id": "PROP_258636"
  },
  {
    "address": "728 Hill St",
    "city": "Austin",
    "state": "TX",
    "zip": "78735",
    "county": "Austin County",
    "latitude": 30.285169,
    "longitude": -97.774164,
    "bedrooms": 5,
    "bathrooms": 1.5,
    "square_feet": 2057,
    "lot_size": 1.15,
    "year_built": 1994,
    "garage_spaces": 3,
    "basement": false,
    "pool": false,
    "fireplace": false,
    "property_type": "Duplex",
    "market_value": 411096,
    "tax_assessment": 359123,
    "insurance_value": 490695,
    "rental_estimate": 4681,
    "hoa_name": "Sunset Hills HOA",
    "hoa_monthly_fee": 379,
    "hoa_special_assessment": 0,
    "hoa_amenities": "Clubhouse, Pool, Gym",
    "hoa_management": "Premier HOA Solutions",
    "exterior_paint": 4937,
    "bathroom_rehab": 3444,
    "roof_repair": 15899,
    "hvac_cost": 10423,
    "flooring_cost": 6036,
    "data_source": "Sample Generator",
    "created_date": "2025-08-20T16:46:16.976808",
    "property_id": "PROP_334336"
  },
  {
    "address": "8737 Highland Dr",
    "city": "Denver",
    "state": "CO",
    "zip": "80234",
    "county": "Denver County",
    "latitude": 39.73901,
    "longitude": -105.048937,
    "bedrooms": 4,
    "bathrooms": 4.0,
    "square_feet": 1811,
    "lot_size": 0.49,
    "year_built": 1993,
    "garage_spaces": 0,
    "basement": true,
    "pool": false,
    "fireplace": false,
    "property_type": "Single Family",
    "market_value": 321937,
    "tax_assessment": 261099,
    "insurance_value": 367269,
    "rental_estimate": 3228,
    "hoa_name": "Maple Grove HOA",
    "hoa_monthly_fee": 264,
    "hoa_special_assessment": 0,
    "hoa_amenities": "Pool, Gym, Tennis Court",
    "hoa_management": "XYZ HOA Services",
    "plumbing_work": 3291,
    "interior_paint": 3569,
    "roof_repair": 16884,
    "data_source": "Sample Generator",
    "created_date": "2025-08-20T16:46:16.976836",
    "property_id": "PROP_329233"
  },
  {
    "address": "151 Elm St",
    "city": "Atlanta",
    "state": "GA",
    "zip": "30391",
    "county": "Atlanta County",
    "latitude": 33.820954,
    "longitude": -84.429439,
    "bedrooms": 2,
    "bathrooms": 4.0,
    "square_feet": 1225,
    "lot_size": 0.27,
    "year_built": 2008,
    "garage_spaces": 1,
    "basement": true,
    "pool": false,
    "fireplace": false,
    "property_type": "Townhouse",
    "market_value": 219804,
    "tax_assessment": 170193,
    "insurance_value": 279733,
    "rental_estimate": 1703,
    "electrical_work": 5203,
    "interior_paint": 4795,
    "hvac_cost": 5182,
    "data_source": "Sample Generator",
    "created_date": "2025-08-20T16:46:16.976861",
    "property_id": "PROP_430184"
  },
  {
    "address": "6641 Hill St",
    "city": "Dallas",
    "state": "TX",
    "zip": "75242",
    "county": "Dallas County",
    "latitude": 32.718858,
    "longitude": -96.83879,
    "bedrooms": 2,
    "bathrooms": 2.0,
    "square_feet": 1285,
    "lot_size": 0.61,
    "year_built": 2013,
    "garage_spaces": 2,
    "basement": false,
    "pool": false,
    "fireplace": true,
    "property_type": "Duplex",
    "market_value": 249316,
    "tax_assessment": 223335,
    "insurance_value": 319016,
    "rental_estimate": 2737,
    "hoa_name": "Cedar Creek Community",
    "hoa_monthly_fee": 202,
    "hoa_special_assessment": 0,
    "hoa_amenities": "Pool, Gym, Tennis Court",
    "hoa_management": "Premier HOA Solutions",
    "interior_paint": 1199,
    "electrical_work": 5045,
    "data_source": "Sample Generator",
    "created_date": "2025-08-20T16:46:16.976888",
    "property_id": "PROP_615496"
  },
  {
    "address": "2146 Hill St",
    "city": "Austin",
    "state": "TX",
    "zip": "78786",
    "county": "Austin County",
    "latitude": 30.262581,
    "longitude": -97.666392,
    "bedrooms": 4,
    "bathrooms": 1.0,
    "square_feet": 2370,
    "lot_size": 1.71,
    "year_built": 1989,
    "garage_spaces": 0,
    "basement": true,
    "pool": false,
    "fireplace": false,
    "property_type": "Multi-Family",
    "market_value": 634667,
    "tax_assessment": 468154,
    "insurance_value": 742949,
    "rental_estimate": 7112,
    "flooring_cost": 11414,
    "roof_repair": 8225,
    "plumbing_work": 5123,
    "hvac_cost": 7865,
    "interior_paint": 2486,
    "data_source": "Sample Generator",
    "created_date": "2025-08-20T16:46:16.976915",
    "property_id": "PROP_274359"
  },
  {
    "address": "4146 Highland Dr",
    "city": "Dallas",
    "state": "TX",
    "zip": "75211",
    "county": "Dallas County",
    "latitude": 32.813244,
    "longitude": -96.794587,
    "bedrooms": 4,
    "bathrooms": 2.0,
    "square_feet": 1977,
    "lot_size": 1.67,
    "year_built": 1984,
    "garage_spaces": 3,
    "basement": true,
    "pool": false,
    "fireplace": true,
    "property_type": "Townhouse",
    "market_value": 281135,
    "tax_assessment": 223894,
    "insurance_value": 357422,
    "rental_estimate": 3048,
    "exterior_paint": 4622,
    "plumbing_work": 5364,
    "kitchen_rehab": 11682,
    "data_source": "Sample Generator",
    "created_date": "2025-08-20T16:46:16.976945",
    "property_id": "PROP_936440"
  }
]